{
    "date": "1/15/2019, 6:41:05 PM",
    "algorithm": "./src/estimateKey5.js",
    "nCorrect": 0,
    "nIncorrect": 2,
    "nError": 0,
    "errors": [],
    "successRate": 0,
    "percentSuccessRate": "0.00%",
    "totalProcessTime": 28.161,
    "trackByTrack": [
        {
            "file": "/Users/joel/Programming/node-key-analysis/music/keyFinder/10cc - Dreadlock Holiday.mp3",
            "correctRoot": 7,
            "correctMode": "minor",
            "correctScaleID": 19,
            "estimatedScaleID": 3,
            "estimatedRoot": 3,
            "estimatedMode": "major",
            "correct": false,
            "difference": "8 major < minor",
            "rootCorrect": false,
            "modeCorrect": false,
            "processTime": 17.287
        },
        {
            "file": "/Users/joel/Programming/node-key-analysis/music/keyFinder/4hero - Star Chasers.mp3",
            "correctRoot": 9,
            "correctMode": "minor",
            "correctScaleID": 21,
            "estimatedScaleID": 12,
            "estimatedRoot": 0,
            "estimatedMode": "minor",
            "correct": false,
            "difference": "3 minor < minor",
            "rootCorrect": false,
            "modeCorrect": true,
            "processTime": 10.874
        }
    ],
    "confusionMatrix": [
        "   *-    -    -    -    -    -    -    -    -    -    -    -    -    -    -    -    -    -    -    -    -    -    -    -",
        "    -   *-    -    -    -    -    -    -    -    -    -    -    -    -    -    -    -    -    -    -    -    -    -    -",
        "    -    -   *-    -    -    -    -    -    -    -    -    -    -    -    -    -    -    -    -    -    -    -    -    -",
        "    -    -    -   *-    -    -    -    -    -    -    -    -    -    -    -    -    -    -    -    -    -    -    -    -",
        "    -    -    -    -   *-    -    -    -    -    -    -    -    -    -    -    -    -    -    -    -    -    -    -    -",
        "    -    -    -    -    -   *-    -    -    -    -    -    -    -    -    -    -    -    -    -    -    -    -    -    -",
        "    -    -    -    -    -    -   *-    -    -    -    -    -    -    -    -    -    -    -    -    -    -    -    -    -",
        "    -    -    -    -    -    -    -   *-    -    -    -    -    -    -    -    -    -    -    -    -    -    -    -    -",
        "    -    -    -    -    -    -    -    -   *-    -    -    -    -    -    -    -    -    -    -    -    -    -    -    -",
        "    -    -    -    -    -    -    -    -    -   *-    -    -    -    -    -    -    -    -    -    -    -    -    -    -",
        "    -    -    -    -    -    -    -    -    -    -   *-    -    -    -    -    -    -    -    -    -    -    -    -    -",
        "    -    -    -    -    -    -    -    -    -    -    -   *-    -    -    -    -    -    -    -    -    -    -    -    -",
        "    -    -    -    -    -    -    -    -    -    -    -    -   *-    -    -    -    -    -    -    -    -    -    -    -",
        "    -    -    -    -    -    -    -    -    -    -    -    -    -   *-    -    -    -    -    -    -    -    -    -    -",
        "    -    -    -    -    -    -    -    -    -    -    -    -    -    -   *-    -    -    -    -    -    -    -    -    -",
        "    -    -    -    -    -    -    -    -    -    -    -    -    -    -    -   *-    -    -    -    -    -    -    -    -",
        "    -    -    -    -    -    -    -    -    -    -    -    -    -    -    -    -   *-    -    -    -    -    -    -    -",
        "    -    -    -    -    -    -    -    -    -    -    -    -    -    -    -    -    -   *-    -    -    -    -    -    -",
        "    -    -    -    -    -    -    -    -    -    -    -    -    -    -    -    -    -    -   *-    -    -    -    -    -",
        "    -    -    -    1    -    -    -    -    -    -    -    -    -    -    -    -    -    -    -   *-    -    -    -    -",
        "    -    -    -    -    -    -    -    -    -    -    -    -    -    -    -    -    -    -    -    -   *-    -    -    -",
        "    -    -    -    -    -    -    -    -    -    -    -    -    1    -    -    -    -    -    -    -    -   *-    -    -",
        "    -    -    -    -    -    -    -    -    -    -    -    -    -    -    -    -    -    -    -    -    -    -   *-    -",
        "    -    -    -    -    -    -    -    -    -    -    -    -    -    -    -    -    -    -    -    -    -    -    -   *-"
    ],
    "differenceMatrix": {
        "8 major < minor": 1,
        "3 minor < minor": 1
    },
    "reportName": "new example data, use harmonics 3",
    "nTotal": 2,
    "averageProcessTime": 14.0805
}